{"class":"shaman","classId":7,"spec":"restoration","specId":264,"treeId":786,"patch":"12.0.7","build":"12.0.7.67808","serialCount":214,"grantedSerials":[100,110],"heroSelector":{"serial":118,"choices":["Farseer","Totemic"]},"trees":{"class":{"nodes":[{"id":103588,"type":"ACTIVE","x":600,"y":0,"serial":136,"req":0,"prereq":[],"entries":[{"id":127861,"name":"Chain Heal","spell":1064,"ranks":1,"choice":0}]},{"id":103598,"type":"ACTIVE","x":1800,"y":0,"serial":142,"req":0,"prereq":[],"entries":[{"id":127873,"name":"Lava Burst","spell":51505,"ranks":1,"choice":0}]},{"id":103583,"type":"ACTIVE","x":3000,"y":0,"serial":131,"req":0,"prereq":[],"entries":[{"id":127856,"name":"Chain Lightning","spell":188443,"ranks":1,"choice":0}]},{"id":103596,"type":"ACTIVE","x":0,"y":600,"serial":141,"req":0,"prereq":[103588],"entries":[{"id":127871,"name":"Earth Shield","spell":974,"ranks":1,"choice":0}]},{"id":103610,"type":"PASSIVE","x":1200,"y":600,"serial":151,"req":0,"prereq":[103598,103588],"entries":[{"id":127886,"name":"Ancestral Wolf Affinity","spell":382197,"ranks":1,"choice":0}]},{"id":103605,"type":"PASSIVE","x":1800,"y":600,"serial":147,"req":0,"prereq":[103598],"entries":[{"id":127880,"name":"Fire and Ice","spell":382886,"ranks":1,"choice":0}]},{"id":103581,"type":"CHOICE","x":2400,"y":600,"serial":129,"req":0,"prereq":[103583,103598],"entries":[{"id":127854,"name":"Spirit Wolf","spell":260878,"ranks":1,"choice":0},{"id":127853,"name":"Thunderous Paws","spell":378075,"ranks":1,"choice":1}]},{"id":109492,"type":"ACTIVE","x":3600,"y":600,"serial":194,"req":0,"prereq":[103583],"entries":[{"id":135718,"name":"Frost Shock","spell":196840,"ranks":1,"choice":0}]},{"id":103602,"type":"PASSIVE","x":0,"y":1200,"serial":146,"req":0,"prereq":[103596],"entries":[{"id":127877,"name":"Elemental Orbit","spell":383010,"ranks":1,"choice":0}]},{"id":103591,"type":"CHOICE","x":600,"y":1200,"serial":138,"req":0,"prereq":[103596,103610],"entries":[{"id":127865,"name":"Spirit Walk","spell":58875,"ranks":1,"choice":0},{"id":127864,"name":"Gust of Wind","spell":192063,"ranks":1,"choice":1}]},{"id":103616,"type":"ACTIVE","x":1800,"y":1200,"serial":157,"req":0,"prereq":[103581,103610,103605],"entries":[{"id":127893,"name":"Astral Shift","spell":108271,"ranks":1,"choice":0}]},{"id":103613,"type":"PASSIVE","x":3000,"y":1200,"serial":154,"req":0,"prereq":[103581,109492],"entries":[{"id":127890,"name":"Nature's Guardian","spell":30884,"ranks":1,"choice":0}]},{"id":109493,"type":"CHOICE","x":3600,"y":1200,"serial":195,"req":0,"prereq":[109492],"entries":[{"id":135719,"name":"Encasing Cold","spell":462762,"ranks":1,"choice":0},{"id":135717,"name":"Arctic Snowstorm","spell":462764,"ranks":1,"choice":1}]},{"id":103590,"type":"ACTIVE","x":0,"y":1800,"serial":137,"req":0,"prereq":[103591,103602],"entries":[{"id":0,"name":"Healing Stream Totem","spell":5394,"ranks":1,"choice":0}]},{"id":103614,"type":"PASSIVE","x":1200,"y":1800,"serial":155,"req":0,"prereq":[103591,103616],"entries":[{"id":127891,"name":"Winds of Al'Akir","spell":382215,"ranks":2,"choice":0}]},{"id":103611,"type":"CHOICE","x":1800,"y":1800,"serial":152,"req":0,"prereq":[103616],"entries":[{"id":127888,"name":"Planes Traveler","spell":381647,"ranks":1,"choice":0},{"id":127887,"name":"Astral Bulwark","spell":377933,"ranks":1,"choice":1}]},{"id":103582,"type":"PASSIVE","x":2400,"y":1800,"serial":130,"req":0,"prereq":[103613,103616],"entries":[{"id":127855,"name":"Brimming with Life","spell":381689,"ranks":2,"choice":0}]},{"id":103615,"type":"ACTIVE","x":3600,"y":1800,"serial":156,"req":0,"prereq":[103613,109493],"entries":[{"id":127892,"name":"Wind Shear","spell":57994,"ranks":1,"choice":0}]},{"id":103601,"type":"PASSIVE","x":0,"y":2400,"serial":145,"req":8,"prereq":[103590],"entries":[{"id":127876,"name":"Elemental Resistance","spell":462368,"ranks":1,"choice":0}]},{"id":103622,"type":"ACTIVE","x":600,"y":2400,"serial":161,"req":8,"prereq":[103614,103590],"entries":[{"id":127902,"name":"Earthgrab Totem","spell":51485,"ranks":1,"choice":0}]},{"id":103579,"type":"ACTIVE","x":1800,"y":2400,"serial":128,"req":8,"prereq":[103614,103611],"entries":[{"id":127851,"name":"Capacitor Totem","spell":192058,"ranks":1,"choice":0}]},{"id":110085,"type":"PASSIVE","x":2400,"y":2400,"serial":209,"req":8,"prereq":[103582,103611],"entries":[{"id":136585,"name":"Spiritual Awakening","spell":1270375,"ranks":1,"choice":0}]},{"id":103606,"type":"PASSIVE","x":3000,"y":2400,"serial":148,"req":8,"prereq":[103615,103582],"entries":[{"id":127881,"name":"Enhanced Imbues","spell":462796,"ranks":1,"choice":0}]},{"id":103628,"type":"PASSIVE","x":3600,"y":2400,"serial":167,"req":8,"prereq":[103615],"entries":[{"id":127910,"name":"Windveil","spell":355630,"ranks":1,"choice":0}]},{"id":103594,"type":"PASSIVE","x":0,"y":3000,"serial":140,"req":8,"prereq":[103601,103622],"entries":[{"id":127869,"name":"Refreshing Waters","spell":378211,"ranks":1,"choice":0}]},{"id":81073,"type":"PASSIVE","x":1200,"y":3000,"serial":80,"req":8,"prereq":[103622,103579],"entries":[{"id":101964,"name":"Improved Purify Spirit","spell":383016,"ranks":1,"choice":0}]},{"id":103618,"type":"PASSIVE","x":1800,"y":3000,"serial":159,"req":8,"prereq":[103579],"entries":[{"id":127896,"name":"Static Charge","spell":265046,"ranks":2,"choice":0}]},{"id":103627,"type":"ACTIVE","x":2400,"y":3000,"serial":166,"req":8,"prereq":[110085,103579],"entries":[{"id":127909,"name":"Wind Rush Totem","spell":192077,"ranks":1,"choice":0}]},{"id":103585,"type":"ACTIVE","x":3000,"y":3000,"serial":133,"req":8,"prereq":[103606,110085],"entries":[{"id":127858,"name":"Earth Elemental","spell":198103,"ranks":1,"choice":0}]},{"id":103624,"type":"CHOICE","x":600,"y":3600,"serial":163,"req":8,"prereq":[81073,103594],"entries":[{"id":127905,"name":"Purge","spell":370,"ranks":1,"choice":0},{"id":127904,"name":"Greater Purge","spell":378773,"ranks":1,"choice":1}]},{"id":103617,"type":"PASSIVE","x":1800,"y":3600,"serial":158,"req":8,"prereq":[81073,103627,103618],"entries":[{"id":127894,"name":"Nature's Fury","spell":381655,"ranks":2,"choice":0}]},{"id":103607,"type":"CHOICE","x":2400,"y":3600,"serial":149,"req":8,"prereq":[103627],"entries":[{"id":127883,"name":"Ascending Air","spell":462791,"ranks":1,"choice":0},{"id":127882,"name":"Jet Stream","spell":462817,"ranks":1,"choice":1}]},{"id":103612,"type":"PASSIVE","x":3000,"y":3600,"serial":153,"req":8,"prereq":[103585],"entries":[{"id":127889,"name":"Primordial Bond","spell":1279819,"ranks":1,"choice":0}]},{"id":103623,"type":"ACTIVE","x":3600,"y":3600,"serial":162,"req":8,"prereq":[103585,103628],"entries":[{"id":127903,"name":"Hex","spell":51514,"ranks":1,"choice":0}]},{"id":103584,"type":"ACTIVE","x":0,"y":4200,"serial":132,"req":23,"prereq":[103594,103624],"entries":[{"id":127857,"name":"Spiritwalker's Grace","spell":79206,"ranks":1,"choice":0}]},{"id":109386,"type":"ACTIVE","x":1200,"y":4200,"serial":190,"req":23,"prereq":[103617,103624],"entries":[{"id":135590,"name":"Totemic Projection","spell":108287,"ranks":1,"choice":0}]},{"id":103586,"type":"PASSIVE","x":1800,"y":4200,"serial":134,"req":23,"prereq":[103617,103607],"entries":[{"id":127859,"name":"Elemental Warding","spell":381650,"ranks":1,"choice":0}]},{"id":103625,"type":"PASSIVE","x":3000,"y":4200,"serial":164,"req":23,"prereq":[103607,103612,103623],"entries":[{"id":127906,"name":"Totemic Focus","spell":382201,"ranks":1,"choice":0}]},{"id":103626,"type":"CHOICE","x":0,"y":4800,"serial":165,"req":23,"prereq":[103584],"entries":[{"id":127908,"name":"Graceful Spirit","spell":192088,"ranks":1,"choice":0},{"id":127907,"name":"Spiritwalker's Aegis","spell":378077,"ranks":1,"choice":1}]},{"id":103587,"type":"PASSIVE","x":1200,"y":4800,"serial":135,"req":23,"prereq":[103586,109386],"entries":[{"id":127860,"name":"Mana Spring","spell":381930,"ranks":1,"choice":0}]},{"id":103599,"type":"CHOICE","x":1800,"y":4800,"serial":143,"req":23,"prereq":[103586],"entries":[{"id":127874,"name":"Tremor Totem","spell":8143,"ranks":1,"choice":0},{"id":136567,"name":"Poison Cleansing Totem","spell":383013,"ranks":1,"choice":1}]},{"id":103593,"type":"CHOICE","x":2400,"y":4800,"serial":139,"req":23,"prereq":[103586,103625],"entries":[{"id":127868,"name":"Therazane's Resilience","spell":1217622,"ranks":1,"choice":0},{"id":136584,"name":"Reactive Warding","spell":462454,"ranks":1,"choice":1}]},{"id":103600,"type":"PASSIVE","x":3600,"y":4800,"serial":144,"req":23,"prereq":[103623],"entries":[{"id":127875,"name":"Voodoo Mastery","spell":204268,"ranks":1,"choice":0}]},{"id":103620,"type":"ACTIVE","x":600,"y":5400,"serial":160,"req":23,"prereq":[103587,103626],"entries":[{"id":127899,"name":"Nature's Swiftness","spell":378081,"ranks":1,"choice":0}]},{"id":109388,"type":"PASSIVE","x":1800,"y":5400,"serial":192,"req":23,"prereq":[103599,103587,103593],"entries":[{"id":135592,"name":"Totemic Surge","spell":381867,"ranks":1,"choice":0}]},{"id":109387,"type":"PASSIVE","x":3000,"y":5400,"serial":191,"req":23,"prereq":[103593,103625,103600],"entries":[{"id":135591,"name":"Instinctive Imbuements","spell":1270350,"ranks":1,"choice":0}]}]},"spec":{"nodes":[{"id":81027,"type":"ACTIVE","x":1800,"y":0,"serial":60,"req":0,"prereq":[],"entries":[{"id":101905,"name":"Riptide","spell":61295,"ranks":1,"choice":0}]},{"id":81040,"type":"ACTIVE","x":1200,"y":600,"serial":67,"req":0,"prereq":[81027],"entries":[{"id":101923,"name":"Healing Rain","spell":73920,"ranks":1,"choice":0}]},{"id":81022,"type":"ACTIVE","x":2400,"y":600,"serial":58,"req":0,"prereq":[81027],"entries":[{"id":0,"name":"Healing Stream Totem","spell":5394,"ranks":1,"choice":0}]},{"id":103428,"type":"PASSIVE","x":600,"y":1200,"serial":121,"req":0,"prereq":[81040],"entries":[{"id":127672,"name":"Soothing Rain","spell":1252874,"ranks":1,"choice":0}]},{"id":81039,"type":"PASSIVE","x":1200,"y":1200,"serial":66,"req":0,"prereq":[81040],"entries":[{"id":101922,"name":"Acid Rain","spell":378443,"ranks":1,"choice":0}]},{"id":81032,"type":"CHOICE","x":1800,"y":1200,"serial":62,"req":0,"prereq":[81022,81040],"entries":[{"id":101912,"name":"Ascendance","spell":114052,"ranks":1,"choice":0},{"id":135486,"name":"Healing Tide Totem","spell":108280,"ranks":1,"choice":1}]},{"id":81021,"type":"PASSIVE","x":3000,"y":1200,"serial":57,"req":0,"prereq":[81022],"entries":[{"id":101899,"name":"Water Totem Mastery","spell":382030,"ranks":1,"choice":0}]},{"id":92677,"type":"PASSIVE","x":0,"y":1800,"serial":83,"req":0,"prereq":[103428],"entries":[{"id":114813,"name":"Overflowing Shores","spell":383222,"ranks":1,"choice":0}]},{"id":103429,"type":"PASSIVE","x":1200,"y":1800,"serial":122,"req":0,"prereq":[81032,103428,81039],"entries":[{"id":127673,"name":"Ancestral Vigor","spell":207401,"ranks":2,"choice":0}]},{"id":81033,"type":"CHOICE","x":1800,"y":1800,"serial":63,"req":0,"prereq":[81032],"entries":[{"id":101913,"name":"First Ascendant","spell":462440,"ranks":1,"choice":0},{"id":135485,"name":"Preeminence","spell":462443,"ranks":1,"choice":1}]},{"id":81024,"type":"PASSIVE","x":2400,"y":1800,"serial":59,"req":0,"prereq":[81032,81021],"entries":[{"id":101902,"name":"Resurgence","spell":16196,"ranks":1,"choice":0}]},{"id":81018,"type":"PASSIVE","x":3600,"y":1800,"serial":55,"req":0,"prereq":[81021],"entries":[{"id":101895,"name":"Living Stream","spell":382482,"ranks":1,"choice":0}]},{"id":81038,"type":"PASSIVE","x":600,"y":2400,"serial":65,"req":8,"prereq":[103429,103428],"entries":[{"id":101920,"name":"Current Control","spell":1253093,"ranks":1,"choice":0}]},{"id":81047,"type":"PASSIVE","x":1800,"y":2400,"serial":73,"req":8,"prereq":[81033,103429,81024],"entries":[{"id":101932,"name":"White Water","spell":462587,"ranks":1,"choice":0}]},{"id":81019,"type":"PASSIVE","x":3000,"y":2400,"serial":56,"req":8,"prereq":[81018,81024],"entries":[{"id":101896,"name":"Calm Waters","spell":1252841,"ranks":1,"choice":0}]},{"id":81048,"type":"PASSIVE","x":3600,"y":2400,"serial":74,"req":8,"prereq":[81018],"entries":[{"id":101934,"name":"Quickstream","spell":1253099,"ranks":1,"choice":0}]},{"id":109301,"type":"PASSIVE","x":0,"y":3000,"serial":189,"req":8,"prereq":[81038,92677],"entries":[{"id":135487,"name":"Rip Current","spell":1254251,"ranks":1,"choice":0}]},{"id":110084,"type":"PASSIVE","x":600,"y":3000,"serial":208,"req":8,"prereq":[81038],"entries":[{"id":136583,"name":"Crashing Waves","spell":1253090,"ranks":1,"choice":0}]},{"id":92675,"type":"ACTIVE","x":1200,"y":3000,"serial":82,"req":8,"prereq":[81038,81047],"entries":[{"id":114811,"name":"Unleash Life","spell":73685,"ranks":1,"choice":0}]},{"id":103432,"type":"PASSIVE","x":1800,"y":3000,"serial":124,"req":8,"prereq":[81047],"entries":[{"id":127678,"name":"Torrent","spell":200072,"ranks":1,"choice":0}]},{"id":81049,"type":"ACTIVE","x":2400,"y":3000,"serial":75,"req":8,"prereq":[81047,81019],"entries":[{"id":101935,"name":"Earthliving Weapon","spell":382021,"ranks":1,"choice":0}]},{"id":81046,"type":"PASSIVE","x":3600,"y":3000,"serial":72,"req":8,"prereq":[81048,81019],"entries":[{"id":101931,"name":"Earthweaver","spell":1254210,"ranks":1,"choice":0}]},{"id":81037,"type":"PASSIVE","x":600,"y":3600,"serial":64,"req":8,"prereq":[92675,110084,109301],"entries":[{"id":101919,"name":"Deluge","spell":200076,"ranks":1,"choice":0}]},{"id":110083,"type":"PASSIVE","x":1200,"y":3600,"serial":207,"req":8,"prereq":[92675],"entries":[{"id":136582,"name":"Earthen Accord","spell":1271104,"ranks":1,"choice":0}]},{"id":81044,"type":"PASSIVE","x":1800,"y":3600,"serial":71,"req":8,"prereq":[81049,92675,103432],"entries":[{"id":101928,"name":"Tidal Waves","spell":51564,"ranks":1,"choice":0}]},{"id":81050,"type":"PASSIVE","x":2400,"y":3600,"serial":76,"req":8,"prereq":[81049],"entries":[{"id":101936,"name":"Improved Earthliving Weapon","spell":382315,"ranks":1,"choice":0}]},{"id":81031,"type":"CHOICE","x":3000,"y":3600,"serial":61,"req":8,"prereq":[81046,81019,81049],"entries":[{"id":101911,"name":"Ancestral Reach","spell":382732,"ranks":1,"choice":0},{"id":101910,"name":"Flow of the Tides","spell":382039,"ranks":1,"choice":1}]},{"id":103436,"type":"ACTIVE","x":0,"y":4200,"serial":127,"req":20,"prereq":[81037,109301],"entries":[{"id":127682,"name":"Downpour","spell":462486,"ranks":1,"choice":0}]},{"id":81055,"type":"PASSIVE","x":1200,"y":4200,"serial":79,"req":20,"prereq":[110083,81037,81044],"entries":[{"id":101942,"name":"Echo of the Elements","spell":333919,"ranks":1,"choice":0}]},{"id":81041,"type":"ACTIVE","x":2400,"y":4200,"serial":68,"req":20,"prereq":[81031,81050,81044],"entries":[{"id":101924,"name":"Spirit Link Totem","spell":98008,"ranks":1,"choice":0}]},{"id":103430,"type":"PASSIVE","x":3600,"y":4200,"serial":123,"req":20,"prereq":[81046,81031],"entries":[{"id":127674,"name":"Earthen Harmony","spell":382020,"ranks":1,"choice":0}]},{"id":103434,"type":"PASSIVE","x":0,"y":4800,"serial":126,"req":20,"prereq":[103436],"entries":[{"id":127680,"name":"Water Expulsion","spell":1253014,"ranks":1,"choice":0}]},{"id":81043,"type":"PASSIVE","x":600,"y":4800,"serial":70,"req":20,"prereq":[81055,103436],"entries":[{"id":101927,"name":"Ancestral Awakening","spell":382309,"ranks":2,"choice":0}]},{"id":103433,"type":"PASSIVE","x":1200,"y":4800,"serial":125,"req":20,"prereq":[81055],"entries":[{"id":127679,"name":"Tidewaters","spell":462424,"ranks":1,"choice":0}]},{"id":81052,"type":"PASSIVE","x":1800,"y":4800,"serial":78,"req":20,"prereq":[81041,81055],"entries":[{"id":101939,"name":"Undercurrent","spell":382194,"ranks":2,"choice":0}]},{"id":103915,"type":"PASSIVE","x":2400,"y":4800,"serial":182,"req":20,"prereq":[81041],"entries":[{"id":128332,"name":"Spouting Spirits","spell":462383,"ranks":1,"choice":0}]},{"id":103427,"type":"PASSIVE","x":3000,"y":4800,"serial":120,"req":20,"prereq":[103430,81041],"entries":[{"id":127671,"name":"Wavespeaker's Blessing","spell":381946,"ranks":2,"choice":0}]},{"id":104124,"type":"PASSIVE","x":0,"y":5400,"serial":183,"req":20,"prereq":[103434],"entries":[{"id":128703,"name":"Double Dip","spell":1252882,"ranks":1,"choice":0}]},{"id":80976,"type":"PASSIVE","x":1200,"y":5400,"serial":27,"req":20,"prereq":[103433,81043,81052],"entries":[{"id":101842,"name":"Primal Tide Core","spell":382045,"ranks":1,"choice":0}]},{"id":81042,"type":"PASSIVE","x":2400,"y":5400,"serial":69,"req":20,"prereq":[103427,103915,81052],"entries":[{"id":101925,"name":"Coalescing Water","spell":470076,"ranks":1,"choice":0}]},{"id":81051,"type":"PASSIVE","x":3600,"y":5400,"serial":77,"req":20,"prereq":[103427,103430],"entries":[{"id":101937,"name":"Deeply Rooted Elements","spell":378270,"ranks":1,"choice":0}]},{"id":110403,"type":"ACTIVE","x":1800,"y":6150,"serial":213,"req":20,"prereq":[],"entries":[{"id":136977,"name":"Stormstream Totem","spell":1267016,"ranks":1,"choice":0}]}]},"hero":{"Totemic":{"nodes":[{"id":94859,"type":"CHOICE","x":0,"y":1200,"serial":85,"req":0,"prereq":[94890],"entries":[{"id":117456,"name":"Oversized Totems","spell":445026,"ranks":1,"choice":0},{"id":125825,"name":"Swift Recall","spell":445027,"ranks":1,"choice":1}]},{"id":94866,"type":"CHOICE","x":600,"y":1800,"serial":90,"req":0,"prereq":[94891],"entries":[{"id":117463,"name":"Pulse Capacitor","spell":445032,"ranks":1,"choice":0},{"id":125824,"name":"Supportive Imbuements","spell":445033,"ranks":1,"choice":1}]},{"id":94871,"type":"PASSIVE","x":0,"y":1800,"serial":95,"req":0,"prereq":[94859],"entries":[{"id":117468,"name":"Imbuement Mastery","spell":445028,"ranks":1,"choice":0}]},{"id":94872,"type":"PASSIVE","x":1200,"y":1200,"serial":96,"req":0,"prereq":[94882],"entries":[{"id":117469,"name":"Splitstream","spell":445035,"ranks":1,"choice":0}]},{"id":94874,"type":"CHOICE","x":600,"y":600,"serial":98,"req":0,"prereq":[94877],"entries":[{"id":117471,"name":"Amplification Core","spell":445029,"ranks":1,"choice":0},{"id":125823,"name":"Oversurge","spell":445030,"ranks":1,"choice":1}]},{"id":94877,"type":"ACTIVE","x":900,"y":0,"serial":100,"req":0,"prereq":[],"entries":[{"id":0,"name":"Surging Totem","spell":444995,"ranks":1,"choice":0}]},{"id":94879,"type":"PASSIVE","x":900,"y":2400,"serial":101,"req":0,"prereq":[94881,94866,94871,109724],"entries":[{"id":117476,"name":"Whirling Elements","spell":445024,"ranks":1,"choice":0}]},{"id":94881,"type":"CHOICE","x":1200,"y":1800,"serial":103,"req":0,"prereq":[94872],"entries":[{"id":117478,"name":"Totemic Coordination","spell":445036,"ranks":1,"choice":0},{"id":125822,"name":"Earthsurge","spell":455590,"ranks":1,"choice":1}]},{"id":94882,"type":"PASSIVE","x":1200,"y":600,"serial":104,"req":0,"prereq":[94877],"entries":[{"id":117479,"name":"Lively Totems","spell":445034,"ranks":1,"choice":0}]},{"id":94890,"type":"PASSIVE","x":0,"y":600,"serial":112,"req":0,"prereq":[94877],"entries":[{"id":117487,"name":"Totemic Rebound","spell":445025,"ranks":1,"choice":0}]},{"id":94891,"type":"PASSIVE","x":600,"y":1200,"serial":113,"req":0,"prereq":[94874],"entries":[{"id":117488,"name":"Wind Barrier","spell":445031,"ranks":1,"choice":0}]},{"id":109724,"type":"PASSIVE","x":1800,"y":1800,"serial":196,"req":0,"prereq":[109725],"entries":[{"id":135982,"name":"Primal Catalyst","spell":1260874,"ranks":1,"choice":0}]},{"id":109725,"type":"PASSIVE","x":1800,"y":1200,"serial":197,"req":0,"prereq":[109726],"entries":[{"id":135983,"name":"Elemental Attunement","spell":1263288,"ranks":1,"choice":0}]},{"id":109726,"type":"PASSIVE","x":1800,"y":600,"serial":198,"req":0,"prereq":[94877],"entries":[{"id":135984,"name":"Totemic Momentum","spell":1260644,"ranks":1,"choice":0}]}]},"Farseer":{"nodes":[{"id":94858,"type":"CHOICE","x":0,"y":1800,"serial":84,"req":0,"prereq":[94887],"entries":[{"id":117455,"name":"Natural Harmony","spell":443442,"ranks":1,"choice":0},{"id":123631,"name":"Earthen Communion","spell":443441,"ranks":1,"choice":1}]},{"id":94860,"type":"PASSIVE","x":600,"y":1198,"serial":86,"req":0,"prereq":[94884],"entries":[{"id":117457,"name":"Primordial Capacity","spell":443448,"ranks":1,"choice":0}]},{"id":94861,"type":"PASSIVE","x":1200,"y":1198,"serial":87,"req":0,"prereq":[94869],"entries":[{"id":117458,"name":"Spiritwalker's Momentum","spell":443425,"ranks":1,"choice":0}]},{"id":94862,"type":"CHOICE","x":0,"y":598,"serial":88,"req":0,"prereq":[94888],"entries":[{"id":117459,"name":"Latent Wisdom","spell":443449,"ranks":1,"choice":0},{"id":123632,"name":"Ancient Fellowship","spell":443423,"ranks":1,"choice":1}]},{"id":94869,"type":"PASSIVE","x":1200,"y":598,"serial":93,"req":0,"prereq":[94888],"entries":[{"id":117466,"name":"Elemental Reverb","spell":443418,"ranks":1,"choice":0}]},{"id":94875,"type":"PASSIVE","x":1200,"y":1800,"serial":99,"req":0,"prereq":[94861],"entries":[{"id":117472,"name":"Final Calling","spell":443446,"ranks":1,"choice":0}]},{"id":94883,"type":"PASSIVE","x":600,"y":1800,"serial":105,"req":0,"prereq":[94860],"entries":[{"id":117480,"name":"Maelstrom Supremacy","spell":443447,"ranks":1,"choice":0}]},{"id":94884,"type":"CHOICE","x":600,"y":600,"serial":106,"req":0,"prereq":[94888],"entries":[{"id":117481,"name":"Heed My Call","spell":443444,"ranks":1,"choice":0},{"id":123630,"name":"Routine Communication","spell":443445,"ranks":1,"choice":1}]},{"id":94887,"type":"PASSIVE","x":0,"y":1198,"serial":109,"req":0,"prereq":[94862],"entries":[{"id":117484,"name":"Offering from Beyond","spell":443451,"ranks":1,"choice":0}]},{"id":94888,"type":"PASSIVE","x":900,"y":0,"serial":110,"req":0,"prereq":[],"entries":[{"id":117485,"name":"Call of the Ancestors","spell":443450,"ranks":1,"choice":0}]},{"id":94894,"type":"ACTIVE","x":900,"y":2400,"serial":116,"req":0,"prereq":[94875,94883,94858,109730],"entries":[{"id":0,"name":"Ancestral Swiftness","spell":443454,"ranks":1,"choice":0}]},{"id":109730,"type":"PASSIVE","x":1800,"y":1800,"serial":202,"req":0,"prereq":[109731],"entries":[{"id":135988,"name":"Mystic Knowledge","spell":1270450,"ranks":1,"choice":0}]},{"id":109731,"type":"PASSIVE","x":1800,"y":1200,"serial":203,"req":0,"prereq":[109732],"entries":[{"id":135989,"name":"Windspeaker","spell":1270447,"ranks":1,"choice":0}]},{"id":109732,"type":"PASSIVE","x":1800,"y":600,"serial":204,"req":0,"prereq":[94888],"entries":[{"id":135990,"name":"Ancestral Influence","spell":1270446,"ranks":1,"choice":0}]}]}}}}
